emsify-1.3.1.dist-info/licenses/LICENSE
mae/__init__.py
mae/drag_drop_uploader.py
mae/ems_automation.py
mae/ems_automation_v1.2.py
mae/ems_walk.py
mae/xpath_builder.py
mae/drivers/__init__.py
mae/drivers/chrome.py
mae/drivers/edge.py
mae/drivers/firefox.py
tests/__init__.py
tests/run_tests.py
tests/test_architecture_concept.py
tests/test_canvas.py
tests/test_ems_automation_v12.py
tests/test_interact.py
tests/test_security_fixes.py
tests/test_shadow_dom.py
tests/test_shadow_in_frames.py
tests/test_window_switch.py
emsify-1.3.1.dist-info/METADATA
emsify-1.3.1.dist-info/WHEEL
emsify-1.3.1.dist-info/top_level.txt
emsify-1.3.1.dist-info/RECORD
