Metadata-Version: 2.4
Name: emsify
Version: 1.3.1
Summary: Modern Automation for EMS - Web scraping toolkit for telecom portals
Author: Ahmedul Kabir Omi
Author-email: Ahmedul Kabir Omi <here.is.omi@gmail.com>
License: MIT
Project-URL: Homepage, https://github.com/hereisomi/emsify
Project-URL: Documentation, https://github.com/hereisomi/emsify/docs
Requires-Python: >=3.7
License-File: LICENSE
Requires-Dist: selenium>=4.0.0
Dynamic: author
Dynamic: license-file
Dynamic: requires-python
